plotextractwithcare/__init__.py
plotextractwithcare/__main__.py
plotextractwithcare/plot_extractor_gui.py
plotextractwithcare-0.1.2.dist-info/licenses/LICENSE
plotextractwithcare-0.1.2.dist-info/METADATA
plotextractwithcare-0.1.2.dist-info/WHEEL
plotextractwithcare-0.1.2.dist-info/entry_points.txt
plotextractwithcare-0.1.2.dist-info/top_level.txt
plotextractwithcare-0.1.2.dist-info/RECORD
