Metadata-Version: 2.4
Name: plotextractwithcare
Version: 0.1.2
Summary: Data extraction tool from image graphs
Author-email: Gadi Lahav <gadi@rfwithcare.com>
License: GPLv3
Requires-Python: >=3.8
License-File: LICENSE
Requires-Dist: numpy
Requires-Dist: PyQt5
Dynamic: license-file
